pydantic_secrets/__init__.py
pydantic_secrets/abstract.py
pydantic_secrets/exceptions.py
pydantic_secrets/main.py
pydantic_secrets/protocols.py
pydantic_secrets/secret_manager/__init__.py
pydantic_secrets/secret_manager/gcp.py
pydantic_secrets/version.py
pydantic_secrets/warnings.py
pydantic_secrets-0.2.1.dist-info/LICENSE
pydantic_secrets-0.2.1.dist-info/METADATA
pydantic_secrets-0.2.1.dist-info/WHEEL
pydantic_secrets-0.2.1.dist-info/RECORD
